sovapy/__init__.py
sovapy/computation/__init__.py
sovapy/computation/cavity.py
sovapy/computation/element_data.py
sovapy/computation/geometry.py
sovapy/computation/nparma_bb.txt
sovapy/computation/rings.py
sovapy/computation/structure_factor.py
sovapy/computation/utils.py
sovapy/computation/xparm_ff.txt
sovapy/computation/cavity_calculation/__init__.py
sovapy/computation/cavity_calculation/algorithm.py
sovapy/computation/cavity_calculation/calculation.py
sovapy/computation/cavity_calculation/discretization.py
sovapy/computation/cavity_calculation/gyrationtensor.py
sovapy/computation/cavity_calculation/extension/__init__.py
sovapy/computation/cavity_calculation/extension/extension_ctypes.py
sovapy/computation/cavity_calculation/extension/extension_python.py
sovapy/computation/cavity_calculation/extension/libalgorithm.dll
sovapy/computation/histogram/__init__.py
sovapy/computation/histogram/histogram.cp312-win_amd64.pyd
sovapy/computation/histogram/setup.py
sovapy/computation/split_and_merge/__init__.py
sovapy/computation/split_and_merge/algorithm.py
sovapy/computation/split_and_merge/pipeline.py
sovapy/computation/split_and_merge/domain_centers/__init__.py
sovapy/computation/split_and_merge/domain_centers/calculate_domain_centers.cp312-win_amd64.pyd
sovapy/computation/split_and_merge/domain_centers/setup.py
sovapy/computation/split_and_merge/util/__init__.py
sovapy/computation/split_and_merge/util/graph.py
sovapy/computation/split_and_merge/util/node_border_iterator.py
sovapy/computation/split_and_merge/util/pos_bool_type.py
sovapy/computation/split_and_merge/util/prohibited.py
sovapy/computation/split_and_merge/util/numpy_extension/__init__.py
sovapy/computation/split_and_merge/util/numpy_extension/find_index_of_first_element_not_equivalent.cp312-win_amd64.pyd
sovapy/computation/split_and_merge/util/numpy_extension/setup.py
sovapy/config/__init__.py
sovapy/config/configobj.py
sovapy/config/configuration.py
sovapy/config/cutoff_history.py
sovapy-0.8.3.dist-info/licenses/LICENSE
sovapy-0.8.3.dist-info/METADATA
sovapy-0.8.3.dist-info/WHEEL
sovapy-0.8.3.dist-info/top_level.txt
sovapy-0.8.3.dist-info/RECORD
