Metadata-Version: 2.4
Name: sovapy
Version: 0.8.3
Summary: SOVA (Structural Order Visualization and Analysis) with python
Home-page: https://github.com/MotokiShiga/sova-cui
Download-URL: https://github.com/MotokiShiga/sova-cui
Author: Motoki Shiga & Hidetoshi Morita
Author-email: Motoki Shiga & Hidetoshi Morita <motoki.shiga@tohoku.ac.jp>
Maintainer: Motoki Shiga
Maintainer-email: Motoki Shiga <motoki.shiga@tohoku.ac.jp>
License: MIT License
Project-URL: Homepage, https://github.com/MotokiShiga/sova-cui
Project-URL: Repository, https://github.com/MotokiShiga/sova-cui.git
Keywords: structure order analysis,material science
Classifier: Intended Audience :: Science/Research
Classifier: License :: OSI Approved :: MIT License
Classifier: Programming Language :: Python :: 3
Classifier: Programming Language :: Python :: 3.11
Classifier: Programming Language :: Python :: 3.12
Classifier: Programming Language :: Python :: 3.13
Classifier: Topic :: Scientific/Engineering
Classifier: Topic :: Scientific/Engineering :: Information Analysis
Classifier: Topic :: Scientific/Engineering :: Physics
Classifier: Topic :: Scientific/Engineering :: Chemistry
Classifier: Topic :: Software Development :: Libraries :: Python Modules
Requires-Python: >=3.11
License-File: LICENSE
Requires-Dist: ase>=3.22.1
Requires-Dist: h5py
Requires-Dist: igraph>=0.11.2
Requires-Dist: matplotlib
Requires-Dist: networkx>=3.1
Requires-Dist: numpy>=1.23.1
Requires-Dist: tqdm
Requires-Dist: scipy>=1.8
Requires-Dist: spglib>=2.0
Requires-Dist: PyCifRW>=4.4.5
Dynamic: author
Dynamic: download-url
Dynamic: home-page
Dynamic: license-file
Dynamic: maintainer
Dynamic: requires-python
